README.md
setup.py
illuminati_and_stuff/__init__.py
illuminati_and_stuff/tween_factory.py
illuminati_and_stuff.egg-info/PKG-INFO
illuminati_and_stuff.egg-info/SOURCES.txt
illuminati_and_stuff.egg-info/dependency_links.txt
illuminati_and_stuff.egg-info/requires.txt
illuminati_and_stuff.egg-info/top_level.txt